{
  "task_id": "TASK-20260401-084",
  "goal": "Run the GitHub remote project version locally and verify it is accessible.",
  "constraints": [
    "Use repository workflow commands before execution.",
    "Prefer running the GitHub default branch content.",
    "Do not perform destructive cleanup unless explicitly requested."
  ],
  "deliverables": [
    "GitHub branch/version run confirmation in chat",
    "Runtime health check results in chat",
    "Task execution artifacts generated by ai scripts"
  ],
  "allowed_write_paths": [
    "ai/tasks",
    "ai/out",
    "open_questions.md"
  ],
  "acceptance_commands": [
    "npm run ai:task:validate -- --task ai/tasks/TASK-20260401-084.json",
    "npm run ai:prompt -- --task ai/tasks/TASK-20260401-084.json",
    "npm run ai:finalize -- --task ai/tasks/TASK-20260401-084.json"
  ],
  "status": "in_progress"
}
